{"gameId":432,"fileName":"ftb-ranks-neoforge-2101.1.3.jar","gameVersions":["NeoForge","1.21.1"],"displayName":"[NEOFORGE][1.21.1] FTB Ranks 2101.1.3","sortableGameVersions":[{"gameVersionPadded":"0","gameVersion":"","gameVersionReleaseDate":"2023-07-25T00:00:00Z","gameVersionName":"NeoForge","gameVersionTypeId":68441},{"gameVersionPadded":"0000000001.0000000021.0000000001","gameVersion":"1.21.1","gameVersionReleaseDate":"2024-08-08T15:17:53.787Z","gameVersionName":"1.21.1","gameVersionTypeId":77784}],"downloadUrl":"https://edge.forgecdn.net/files/6431/744/ftb-ranks-neoforge-2101.1.3.jar","fileDate":"2025-04-17T08:15:07.333Z","exposeAsAlternative":null,"modId":314905,"modules":[{"name":"META-INF","fingerprint":2222398491},{"name":"architectury_inject_FTBRanks121_common_ee183a3ff57f463b9935be317c69ea61_0b8a89423a40f8f88b5481b3efc694e73b6e68b53c6aad5866f6a88b1cecc8beftbranks210113devjar","fingerprint":2052477246},{"name":"dev","fingerprint":3487773522},{"name":"ftb-ranks-common-refmap.json","fingerprint":2118009028},{"name":"ftbranks-common.mixins.json","fingerprint":2091257518},{"name":"pack.mcmeta","fingerprint":4253185173}],"dependencies":[{"relationType":3,"modId":419699},{"relationType":3,"modId":404465}],"fileFingerprint":2020141909,"releaseType":1,"hashes":[{"value":"07fdfa3a75c3481770ce0118090a347d89e3a560","algo":1},{"value":"c273b7fb4b76bc82728bf2215fce7280","algo":2}],"parentProjectFileId":null,"alternateFileId":0,"id":6431744,"fileLength":88382,"downloadCount":403262,"serverPackFileId":null,"serverPack":false,"available":false}