{"gameId":432,"fileName":"irons_spells_js-4.0.3.jar","gameVersions":["Client","1.21.1","NeoForge","Server"],"displayName":"KubeJS Iron's Spells 4.0.3","sortableGameVersions":[{"gameVersionPadded":"0","gameVersion":"","gameVersionReleaseDate":"2022-12-08T00:00:00Z","gameVersionName":"Client","gameVersionTypeId":75208},{"gameVersionPadded":"0000000001.0000000021.0000000001","gameVersion":"1.21.1","gameVersionReleaseDate":"2024-08-08T15:17:53.787Z","gameVersionName":"1.21.1","gameVersionTypeId":77784},{"gameVersionPadded":"0","gameVersion":"","gameVersionReleaseDate":"2023-07-25T00:00:00Z","gameVersionName":"NeoForge","gameVersionTypeId":68441},{"gameVersionPadded":"0","gameVersion":"","gameVersionReleaseDate":"2022-12-08T00:00:00Z","gameVersionName":"Server","gameVersionTypeId":75208}],"downloadUrl":"https://edge.forgecdn.net/files/7234/865/irons_spells_js-4.0.3.jar","fileDate":"2025-11-18T06:50:35.783Z","exposeAsAlternative":null,"modId":980834,"modules":[{"name":"META-INF","fingerprint":1931944110},{"name":"com","fingerprint":1697243690},{"name":"icon.png","fingerprint":1284976770},{"name":"irons_spells_js.mixins.json","fingerprint":2298804952},{"name":"kubejs.plugins.txt","fingerprint":509913633}],"dependencies":[{"relationType":3,"modId":855414},{"relationType":3,"modId":238086}],"fileFingerprint":604812262,"releaseType":1,"hashes":[{"value":"0481395c5847e2920d1425e77833bef87df63139","algo":1},{"value":"357989fbe3808757b47f83699a82484e","algo":2}],"parentProjectFileId":null,"alternateFileId":0,"id":7234865,"fileLength":150121,"downloadCount":150365,"serverPackFileId":null,"available":false,"serverPack":false}