{"gameId":432,"fileName":"log_deduplicator-1.21.1-Neoforge-1.0.3.jar","gameVersions":["1.21.1","NeoForge"],"displayName":"log_deduplicator-1.21.1-Neoforge-1.0.3.jar","sortableGameVersions":[{"gameVersionPadded":"0000000001.0000000021.0000000001","gameVersion":"1.21.1","gameVersionReleaseDate":"2024-08-08T15:17:53.787Z","gameVersionName":"1.21.1","gameVersionTypeId":77784},{"gameVersionPadded":"0","gameVersion":"","gameVersionReleaseDate":"2023-07-25T00:00:00Z","gameVersionName":"NeoForge","gameVersionTypeId":68441}],"downloadUrl":"https://edge.forgecdn.net/files/7872/301/log_deduplicator-1.21.1-Neoforge-1.0.3.jar","fileDate":"2026-04-04T10:50:16.550Z","exposeAsAlternative":null,"modId":1493534,"modules":[{"name":"META-INF","fingerprint":3268069872},{"name":"com","fingerprint":2971620184},{"name":"log_deduplicator.mixins.json","fingerprint":148232003},{"name":"logo.png","fingerprint":577903881},{"name":"pack.mcmeta","fingerprint":2823904671},{"name":"LICENSE_Log Deduplicator","fingerprint":18375977}],"dependencies":[{"relationType":3,"modId":667299}],"fileFingerprint":2436129984,"releaseType":1,"hashes":[{"value":"5f53e5dca6bbe1a7a4a42a7126da8e1aa4268d21","algo":1},{"value":"638a2bc364ba8474ec09431f3a1fe2b9","algo":2}],"parentProjectFileId":null,"alternateFileId":0,"id":7872301,"fileLength":289965,"downloadCount":0,"serverPackFileId":null,"serverPack":false,"available":false}