{"gameId":432,"fileName":"xaerominimap-neoforge-1.21.1-25.3.10.jar","gameVersions":["1.21","1.21.1","NeoForge"],"displayName":"neoforge-1.21.1-25.3.10.jar","sortableGameVersions":[{"gameVersionPadded":"0000000001.0000000021","gameVersion":"1.21","gameVersionReleaseDate":"2024-06-14T00:00:00Z","gameVersionName":"1.21","gameVersionTypeId":77784},{"gameVersionPadded":"0000000001.0000000021.0000000001","gameVersion":"1.21.1","gameVersionReleaseDate":"2024-08-08T15:17:53.787Z","gameVersionName":"1.21.1","gameVersionTypeId":77784},{"gameVersionPadded":"0","gameVersion":"","gameVersionReleaseDate":"2023-07-25T00:00:00Z","gameVersionName":"NeoForge","gameVersionTypeId":68441}],"downloadUrl":"https://edge.forgecdn.net/files/7598/595/xaerominimap-neoforge-1.21.1-25.3.10.jar","fileDate":"2026-02-09T09:30:14.857Z","exposeAsAlternative":null,"modId":263420,"modules":[{"name":"META-INF","fingerprint":1234574236},{"name":"LICENSE_xaerohud","fingerprint":2362711594},{"name":"assets","fingerprint":3101686611},{"name":"pack.mcmeta","fingerprint":1956780562},{"name":"xaero","fingerprint":2168124},{"name":"xaerohud.mixins.json","fingerprint":368816408},{"name":"xaerohud.neoforge.mixins.json","fingerprint":1871963410},{"name":"xaerominimap.mixins.json","fingerprint":2847352557},{"name":"xaerominimap.neoforge.mixins.json","fingerprint":1845903568}],"dependencies":[{"relationType":2,"modId":317780},{"relationType":2,"modId":636608}],"fileFingerprint":3098166372,"releaseType":1,"hashes":[{"value":"d4828332dd831455429156b6cfa24aa9bd99dd77","algo":1},{"value":"bb44c90c8bc60cac6caa07f504f5cf9f","algo":2}],"parentProjectFileId":null,"alternateFileId":0,"id":7598595,"fileLength":2137784,"downloadCount":0,"serverPackFileId":null,"available":false,"serverPack":false}