{"allowModDistribution":true,"screenshots":[],"classId":6,"latestFilesIndexes":[{"filename":"melody_neoforge_1.0.16_MC_26.1.1.jar","releaseType":1,"gameVersion":"26.1.1","gameVersionTypeId":83806,"modLoader":6,"fileId":7875755},{"filename":"melody_neoforge_1.0.16_MC_26.1.1.jar","releaseType":1,"gameVersion":"26.1.2","gameVersionTypeId":83806,"modLoader":6,"fileId":7875755},{"filename":"melody_fabric_1.0.16_MC_26.1.1.jar","releaseType":1,"gameVersion":"26.1.1","gameVersionTypeId":83806,"modLoader":4,"fileId":7875748},{"filename":"melody_fabric_1.0.16_MC_26.1.1.jar","releaseType":1,"gameVersion":"26.1.2","gameVersionTypeId":83806,"modLoader":4,"fileId":7875748},{"filename":"melody_neoforge_1.0.15_MC_1.21.11.jar","releaseType":1,"gameVersion":"1.21.11","gameVersionTypeId":77784,"modLoader":6,"fileId":7368694},{"filename":"melody_fabric_1.0.15_MC_1.21.11.jar","releaseType":1,"gameVersion":"1.21.11","gameVersionTypeId":77784,"modLoader":4,"fileId":7368690},{"filename":"melody_neoforge_1.0.14_MC_1.21.10.jar","releaseType":1,"gameVersion":"1.21.10","gameVersionTypeId":77784,"modLoader":6,"fileId":7173097},{"filename":"melody_fabric_1.0.14_MC_1.21.10.jar","releaseType":1,"gameVersion":"1.21.10","gameVersionTypeId":77784,"modLoader":4,"fileId":7173094},{"filename":"melody_neoforge_1.0.12_MC_1.21.6.jar","releaseType":1,"gameVersion":"1.21.8","gameVersionTypeId":77784,"modLoader":6,"fileId":6668769},{"filename":"melody_neoforge_1.0.12_MC_1.21.6.jar","releaseType":1,"gameVersion":"1.21.7","gameVersionTypeId":77784,"modLoader":6,"fileId":6668769},{"filename":"melody_neoforge_1.0.12_MC_1.21.6.jar","releaseType":1,"gameVersion":"1.21.6","gameVersionTypeId":77784,"modLoader":6,"fileId":6668769},{"filename":"melody_forge_1.0.12_MC_1.21.6.jar","releaseType":1,"gameVersion":"1.21.8","gameVersionTypeId":77784,"modLoader":1,"fileId":6668766},{"filename":"melody_forge_1.0.12_MC_1.21.6.jar","releaseType":1,"gameVersion":"1.21.7","gameVersionTypeId":77784,"modLoader":1,"fileId":6668766},{"filename":"melody_forge_1.0.12_MC_1.21.6.jar","releaseType":1,"gameVersion":"1.21.6","gameVersionTypeId":77784,"modLoader":1,"fileId":6668766},{"filename":"melody_fabric_1.0.12_MC_1.21.6.jar","releaseType":1,"gameVersion":"1.21.8","gameVersionTypeId":77784,"modLoader":4,"fileId":6668759},{"filename":"melody_fabric_1.0.12_MC_1.21.6.jar","releaseType":1,"gameVersion":"1.21.7","gameVersionTypeId":77784,"modLoader":4,"fileId":6668759},{"filename":"melody_fabric_1.0.12_MC_1.21.6.jar","releaseType":1,"gameVersion":"1.21.6","gameVersionTypeId":77784,"modLoader":4,"fileId":6668759},{"filename":"melody_neoforge_1.0.11_MC_1.21.5.jar","releaseType":1,"gameVersion":"1.21.5","gameVersionTypeId":77784,"modLoader":6,"fileId":6464606},{"filename":"melody_forge_1.0.11_MC_1.21.5.jar","releaseType":1,"gameVersion":"1.21.5","gameVersionTypeId":77784,"modLoader":1,"fileId":6464597},{"filename":"melody_fabric_1.0.11_MC_1.21.5.jar","releaseType":1,"gameVersion":"1.21.5","gameVersionTypeId":77784,"modLoader":4,"fileId":6464593},{"filename":"melody_neoforge_1.0.10_MC_1.21.jar","releaseType":1,"gameVersion":"1.21","gameVersionTypeId":77784,"modLoader":6,"fileId":5453382},{"filename":"melody_neoforge_1.0.10_MC_1.21.jar","releaseType":1,"gameVersion":"1.21.4","gameVersionTypeId":77784,"modLoader":6,"fileId":5453382},{"filename":"melody_neoforge_1.0.10_MC_1.21.jar","releaseType":1,"gameVersion":"1.21.1","gameVersionTypeId":77784,"modLoader":6,"fileId":5453382},{"filename":"melody_forge_1.0.10_MC_1.21.jar","releaseType":1,"gameVersion":"1.21","gameVersionTypeId":77784,"modLoader":1,"fileId":5430441},{"filename":"melody_forge_1.0.10_MC_1.21.jar","releaseType":1,"gameVersion":"1.21.4","gameVersionTypeId":77784,"modLoader":1,"fileId":5430441},{"filename":"melody_forge_1.0.10_MC_1.21.jar","releaseType":1,"gameVersion":"1.21.1","gameVersionTypeId":77784,"modLoader":1,"fileId":5430441},{"filename":"melody_fabric_1.0.10_MC_1.21.jar","releaseType":1,"gameVersion":"1.21","gameVersionTypeId":77784,"modLoader":4,"fileId":5430438},{"filename":"melody_fabric_1.0.10_MC_1.21.jar","releaseType":1,"gameVersion":"1.21.4","gameVersionTypeId":77784,"modLoader":4,"fileId":5430438},{"filename":"melody_fabric_1.0.10_MC_1.21.jar","releaseType":1,"gameVersion":"1.21.1","gameVersionTypeId":77784,"modLoader":4,"fileId":5430438},{"filename":"melody_forge_1.0.9_MC_1.20.6.jar","releaseType":1,"gameVersion":"1.20.6","gameVersionTypeId":75125,"modLoader":1,"fileId":5347345},{"filename":"melody_neoforge_1.0.6_MC_1.20.5.jar","releaseType":1,"gameVersion":"1.20.6","gameVersionTypeId":75125,"modLoader":6,"fileId":5294554},{"filename":"melody_neoforge_1.0.6_MC_1.20.5.jar","releaseType":1,"gameVersion":"1.20.5","gameVersionTypeId":75125,"modLoader":6,"fileId":5294554},{"filename":"melody_fabric_1.0.6_MC_1.20.5.jar","releaseType":1,"gameVersion":"1.20.6","gameVersionTypeId":75125,"modLoader":4,"fileId":5294552},{"filename":"melody_fabric_1.0.6_MC_1.20.5.jar","releaseType":1,"gameVersion":"1.20.5","gameVersionTypeId":75125,"modLoader":4,"fileId":5294552},{"filename":"melody_neoforge_1.0.5_MC_1.20.4.jar","releaseType":1,"gameVersion":"1.20.4","gameVersionTypeId":75125,"modLoader":6,"fileId":5145418},{"filename":"melody_fabric_1.0.4_MC_1.20.1-1.20.4.jar","releaseType":1,"gameVersion":"1.20.2","gameVersionTypeId":75125,"modLoader":4,"fileId":5139711},{"filename":"melody_fabric_1.0.4_MC_1.20.1-1.20.4.jar","releaseType":1,"gameVersion":"1.20.3","gameVersionTypeId":75125,"modLoader":4,"fileId":5139711},{"filename":"melody_fabric_1.0.4_MC_1.20.1-1.20.4.jar","releaseType":1,"gameVersion":"1.20.1","gameVersionTypeId":75125,"modLoader":4,"fileId":5139711},{"filename":"melody_fabric_1.0.4_MC_1.20.1-1.20.4.jar","releaseType":1,"gameVersion":"1.20.4","gameVersionTypeId":75125,"modLoader":4,"fileId":5139711},{"filename":"melody_forge_1.0.3_MC_1.20.1-1.20.4.jar","releaseType":1,"gameVersion":"1.20.2","gameVersionTypeId":75125,"modLoader":1,"fileId":5109692},{"filename":"melody_forge_1.0.3_MC_1.20.1-1.20.4.jar","releaseType":1,"gameVersion":"1.20.3","gameVersionTypeId":75125,"modLoader":1,"fileId":5109692},{"filename":"melody_forge_1.0.3_MC_1.20.1-1.20.4.jar","releaseType":1,"gameVersion":"1.20.1","gameVersionTypeId":75125,"modLoader":1,"fileId":5109692},{"filename":"melody_forge_1.0.3_MC_1.20.1-1.20.4.jar","releaseType":1,"gameVersion":"1.20.4","gameVersionTypeId":75125,"modLoader":1,"fileId":5109692},{"filename":"melody_forge_1.0.1_MC_1.18.2.jar","releaseType":1,"gameVersion":"1.18.2","gameVersionTypeId":73250,"modLoader":1,"fileId":4984009},{"filename":"melody_fabric_1.0.1_MC_1.18.2.jar","releaseType":1,"gameVersion":"1.18.2","gameVersionTypeId":73250,"modLoader":4,"fileId":4984004},{"filename":"melody_forge_1.0.1_MC_1.19.2.jar","releaseType":1,"gameVersion":"1.19.2","gameVersionTypeId":73407,"modLoader":1,"fileId":4983999},{"filename":"melody_fabric_1.0.1_MC_1.19.2.jar","releaseType":1,"gameVersion":"1.19.2","gameVersionTypeId":73407,"modLoader":4,"fileId":4983993},{"filename":"Melody-fabric-1.19.4-1.0.0.jar","releaseType":1,"gameVersion":"1.19.4","gameVersionTypeId":73407,"modLoader":4,"fileId":4869648},{"filename":"Melody-forge-1.19.4-1.0.0.jar","releaseType":1,"gameVersion":"1.19.4","gameVersionTypeId":73407,"modLoader":1,"fileId":4869647}],"dateCreated":"2023-11-15T10:19:55.147Z","logo":{"description":"","id":1479762,"title":"638961722002206873.png","modId":938643,"url":"https://media.forgecdn.net/avatars/1479/762/638961722002206873.png","thumbnailUrl":"https://media.forgecdn.net/avatars/thumbnails/1479/762/256/256/638961722002206873.png"},"links":{"sourceUrl":"https://github.com/Keksuccino/Melody","issuesUrl":"https://github.com/Keksuccino/Melody/issues","websiteUrl":"https://www.curseforge.com/minecraft/mc-mods/melody","wikiUrl":null},"dateReleased":"2026-04-04T19:55:40.617Z","id":938643,"categories":[{"gameId":432,"classId":6,"name":"API and Library","dateModified":"2014-05-23T03:21:44.06Z","parentCategoryId":6,"id":421,"iconUrl":"https://media.forgecdn.net/avatars/6/36/635351496947765531.png","slug":"library-api","url":"https://www.curseforge.com/minecraft/mc-mods/library-api","displayIndex":0,"class":false}],"slug":"melody","gameId":432,"summary":"OpenAL-based library mod for playing background music.","latestFiles":[{"gameId":432,"fileName":"melody_forge_1.0.12_MC_1.21.6.jar","gameVersions":["1.21.8","Forge","1.21.7","1.21.6"],"displayName":"[Forge] v1.0.12 MC 1.21.6","sortableGameVersions":[{"gameVersionPadded":"0000000001.0000000021.0000000008","gameVersion":"1.21.8","gameVersionReleaseDate":"2025-07-17T14:01:29.007Z","gameVersionName":"1.21.8","gameVersionTypeId":77784},{"gameVersionPadded":"0","gameVersion":"","gameVersionReleaseDate":"2022-10-01T00:00:00Z","gameVersionName":"Forge","gameVersionTypeId":68441},{"gameVersionPadded":"0000000001.0000000021.0000000007","gameVersion":"1.21.7","gameVersionReleaseDate":"2025-06-30T14:45:05.54Z","gameVersionName":"1.21.7","gameVersionTypeId":77784},{"gameVersionPadded":"0000000001.0000000021.0000000006","gameVersion":"1.21.6","gameVersionReleaseDate":"2025-06-17T19:44:59.623Z","gameVersionName":"1.21.6","gameVersionTypeId":77784}],"downloadUrl":"https://edge.forgecdn.net/files/6668/766/melody_forge_1.0.12_MC_1.21.6.jar","fileDate":"2025-06-18T23:10:21.583Z","exposeAsAlternative":null,"modId":938643,"modules":[{"name":"META-INF","fingerprint":3847979419},{"name":"de","fingerprint":2029311762},{"name":"melody.forge.mixins.json","fingerprint":3867677899},{"name":"melody.mixins.json","fingerprint":1917425947},{"name":"melody_logo_128x128.png","fingerprint":964220136},{"name":"pack.mcmeta","fingerprint":2077343754}],"dependencies":[],"fileFingerprint":3818729248,"releaseType":1,"hashes":[{"value":"60b3bba356ddb63f9cd4071a53b0d2b4343297a9","algo":1},{"value":"3744b696a546b19fb42a6c637c0b8eba","algo":2}],"parentProjectFileId":null,"alternateFileId":0,"id":6668766,"fileLength":189825,"downloadCount":6796,"serverPackFileId":null,"serverPack":false,"available":false},{"gameId":432,"fileName":"melody_fabric_1.0.16_MC_26.1.1.jar","gameVersions":["Fabric","26.1.1","26.1.2"],"displayName":"[Fabric] v1.0.16 MC 26.1.1","sortableGameVersions":[{"gameVersionPadded":"0","gameVersion":"","gameVersionReleaseDate":"2022-09-01T00:00:00Z","gameVersionName":"Fabric","gameVersionTypeId":68441},{"gameVersionPadded":"0000000026.0000000001.0000000001","gameVersion":"26.1.1","gameVersionReleaseDate":"2026-04-01T11:40:06.78Z","gameVersionName":"26.1.1","gameVersionTypeId":83806},{"gameVersionPadded":"0000000026.0000000001.0000000002","gameVersion":"26.1.2","gameVersionReleaseDate":"2026-04-09T11:39:54.243Z","gameVersionName":"26.1.2","gameVersionTypeId":83806}],"downloadUrl":"https://edge.forgecdn.net/files/7875/748/melody_fabric_1.0.16_MC_26.1.1.jar","fileDate":"2026-04-04T19:55:10.700Z","exposeAsAlternative":null,"modId":938643,"modules":[{"name":"META-INF","fingerprint":2405684720},{"name":"de","fingerprint":4259144410},{"name":"fabric.mod.json","fingerprint":1625766925},{"name":"melody.fabric.mixins.json","fingerprint":3899949537},{"name":"melody.mixins.json","fingerprint":1333337923},{"name":"melody_logo_128x128.png","fingerprint":1274982181},{"name":"pack.mcmeta","fingerprint":2077343754}],"dependencies":[{"relationType":3,"modId":306612}],"fileFingerprint":1483083471,"releaseType":1,"hashes":[{"value":"217859fbab6a2047a9c64a97d26aaadd34329148","algo":1},{"value":"03db93ae03f40d6bba983043737e491b","algo":2}],"parentProjectFileId":null,"alternateFileId":0,"id":7875748,"fileLength":228922,"downloadCount":2343,"serverPackFileId":null,"serverPack":false,"available":false},{"gameId":432,"fileName":"melody_neoforge_1.0.16_MC_26.1.1.jar","gameVersions":["NeoForge","26.1.1","26.1.2"],"displayName":"[NeoForge] v1.0.16 MC 26.1.1","sortableGameVersions":[{"gameVersionPadded":"0","gameVersion":"","gameVersionReleaseDate":"2023-07-25T00:00:00Z","gameVersionName":"NeoForge","gameVersionTypeId":68441},{"gameVersionPadded":"0000000026.0000000001.0000000001","gameVersion":"26.1.1","gameVersionReleaseDate":"2026-04-01T11:40:06.78Z","gameVersionName":"26.1.1","gameVersionTypeId":83806},{"gameVersionPadded":"0000000026.0000000001.0000000002","gameVersion":"26.1.2","gameVersionReleaseDate":"2026-04-09T11:39:54.243Z","gameVersionName":"26.1.2","gameVersionTypeId":83806}],"downloadUrl":"https://edge.forgecdn.net/files/7875/755/melody_neoforge_1.0.16_MC_26.1.1.jar","fileDate":"2026-04-04T19:55:39.727Z","exposeAsAlternative":null,"modId":938643,"modules":[{"name":"META-INF","fingerprint":3753263175},{"name":"de","fingerprint":2888567550},{"name":"melody.mixins.json","fingerprint":1333337923},{"name":"melody.neoforge.mixins.json","fingerprint":1578470146},{"name":"melody_logo_128x128.png","fingerprint":1274982181},{"name":"pack.mcmeta","fingerprint":2077343754}],"dependencies":[],"fileFingerprint":4006629022,"releaseType":1,"hashes":[{"value":"293746acacd4bab10a429d157f248116872b2b5c","algo":1},{"value":"135539790662277376279725c28618b2","algo":2}],"parentProjectFileId":null,"alternateFileId":0,"id":7875755,"fileLength":47054,"downloadCount":1772,"serverPackFileId":null,"serverPack":false,"available":false}],"dateModified":"2026-04-10T03:50:05.537Z","gamePopularityRank":25,"thumbsUpCount":0,"name":"Melody","mainFileId":7875755,"primaryCategoryId":421,"downloadCount":112517394,"status":4,"authors":[{"name":"Keksuccino","id":100802238,"url":"https://www.curseforge.com/members/keksuccino"}],"available":false,"featured":false}